audtekapi/__init__.py
audtekapi-0.3.0.dist-info/LICENSE
audtekapi-0.3.0.dist-info/METADATA
audtekapi-0.3.0.dist-info/WHEEL
audtekapi-0.3.0.dist-info/top_level.txt
audtekapi-0.3.0.dist-info/RECORD
