Metadata-Version: 2.1
Name: audtekapi
Version: 0.3.0
Summary: Unofficial API for Audioteka
Home-page: https://github.com/jedrus2000/audtekapi
Author: Andrzej Bargański
Author-email: a.barganski@gmail.com
License: Apache License, Version 2.0
Platform: UNKNOWN
Classifier: Environment :: No Input/Output (Daemon)
Classifier: Intended Audience :: End Users/Desktop
Classifier: License :: OSI Approved :: Apache Software License
Classifier: Operating System :: OS Independent
Classifier: Programming Language :: Python :: 3.7
Classifier: Programming Language :: Python :: 3.8
Classifier: Programming Language :: Python :: 3.9
Classifier: Topic :: Multimedia :: Sound/Audio
Requires-Python: ~=3.7
License-File: LICENSE
Requires-Dist: setuptools
Requires-Dist: requests (>=2.25.0)
